{
 "name": "Five Top Topics",
 "children": [
  {
      "name": "First Rank (Movie)",
   "children": [
    {    
     "name": "Topic 477",
     "children": [


  


      {"name": "movi", "value": 3938},
      {"name": film ", "value": 3812},
      {"name": "watch ", "value": 6714}, 
      {"name": "trailer ", "value": 6714}, 
      {"name": "good  ", "value": 6714}, 
      {"name": "love ", "value": 6714}, 

      {"name": "wait ", "value": 6714}, 
      {"name": "great ", "value": 6714}, 
      {"name": "amaz   ", "value": 6714}, 

      {"name": "stori  ", "value": 6714}
  
   
      {"name": " god ", "value": 6714}
      {"name": "time  ", "value": 6714}
      {"name": "play  ", "value": 6714}
      {"name": "pleas  ", "value": 6714}
      {"name": "bad  ", "value": 6714}
      {"name": "fuck  ", "value": 6714}
    
          {"name": "feel  ", "value": 6714}
          {"name": "wow  ", "value": 6714}
          {"name": "work  ", "value": 6714}
          {"name": "life  ", "value": 6714}
  
     ]
    }
  
  
    
    
    
  
     ]
    }
,
  
  
  
  
 
  
  
  
   {
      "name": "Second Rank (people)",
   "children": [
    {
           
      "name": "Topic 328",
     "children": [

       {"name": "peopl ", "value": 3534},
     {"name": "watch ", "value": 5731},
      {"name": "comment ", "value": 7840},
      {"name": "hate ", "value": 5914},
      {"name": "befor ", "value": 3416},
      {"name": "time ", "value": 3416},
      {"name": "mani ", "value": 3416},
      {"name": "man ", "value": 3416},
      {"name": "happen ", "value": 3416},
      {"name": "stop ", "value": 3416},
      {"name": "interest ", "value": 3416},
      {"name": "pretti ", "value": 3416},
      {"name": "hell ", "value": 3416},
      {"name": "person ", "value": 3416},


      {"name": "die ", "value": 3416},
      {"name": "mind ", "value": 3416},
      {"name": "talk ", "value": 3416},
      {"name": "start ", "value": 3416},

      {"name": "day ", "value": 3416},
      {"name": "men ", "value": 3416}
      
                 
 
      
      
     ]
    }
     ]
    } ,
  
  
  
  
  
  
   
   {
      "name": "Third Rank (Song)",
   "children": [
    {
           
      "name": "Topic 1231",
     "children": [

 


      {"name": "actor ", "value": 3938},
      {"name": "guy ", "value": 3812},
      {"name": "hope ", "value": 3812},
      {"name": "director ", "value": 3812},

      {"name": "music ", "value": 3812},
      {"name": "act ", "value": 3812},
      {"name": "bore ", "value": 3812},

      {"name": "great ", "value": 3812},
      {"name": "sound ", "value": 3812},
      {"name": "time ", "value": 3812},
      {"name": "day ", "value": 3812},
      {"name": "cinema ", "value": 3812},
      {"name": "theater ", "value": 3812},


      {"name": "big ", "value": 3812},
      {"name": "save ", "value": 3812},

      {"name": "song ", "value": 3812},
      {"name": "shot ", "value": 3812},

      {"name": "money ", "value": 3812},
      {"name": "role ", "value": 3812},
      {"name": "job", "value": 3812}
                 
 
      
      
     ]
    }
  
     ]
    },
  
  
  
      

  
   {
      "name": "Fourth Rank",
   "children": [
    {
           
      "name": "Topic 169 (Shit)",
     "children": [

      {"name": "shit", "value": 3938},

      {"name": "girl ", "value": 3812},

      {"name": "feel ", "value": 3812},

      {"name": "plot ", "value": 3812},

      {"name": "suppos ", "value": 3812},


      {"name": "friend ", "value": 3812},


      {"name": "weird ", "value": 3812},


      {"name": "glad ", "value": 3812},


      {"name": "women ", "value": 3812},


      {"name": "dumb ", "value": 3812},

      {"name": "definit ", "value": 3812},


      {"name": "confus ", "value": 3812},


      {"name": "honestli ", "value": 3812},


      {"name": "relat ", "value": 3812},
      {"name": "night", "value": 3812},




      {"name": "kinda ", "value": 3812},
      {"name": "spoil", "value": 3812},



      {"name": "joke ", "value": 3812},
      {"name": "eye", "value": 3812},


      {"name": "type ", "value": 3812}
                 
 
      
      
     ]
    }
  
     ]
    },
  
  
  
  




   
   {
      "name": "Fifth Rank",
   "children": [
    {
           
      "name": "Topic 1924",
     "children": [
      {"name": "drinking", "value": 3938},
      {"name": "work", "value": 3812},
      {"name": "understand", "value": 3812},
      {"name": "experience", "value": 3812},
      {"name": "amazing", "value": 3812},
      {"name": "start", "value": 3812},
      {"name": "break", "value": 3812},
      {"name": "state", "value": 3812},
      {"name": "advise", "value": 3812},
      {"name": "hoping", "value": 3812},
      {"name": "bottom", "value": 3812},
      {"name": "pleased", "value": 3812},
      {"name": "reduced", "value": 3812},
      {"name": "personal", "value": 3812},
      {"name": "appreciated", "value": 3812},
      {"name": "time", "value": 3812},
      {"name": "moderate", "value": 3812},
      {"name": "picked", "value": 3812},
      {"name": "boat", "value": 3812},
      {"name": "boat", "depressants": 3812}
      
                 
 
      
      
     ]
    }
  
     ]
    }




  
  
  
  
  
  
  
  
  
  
  
  
  
  
 ]
}


